{
  "endpoint": "/api/admin/settings",
  "status": 200,
  "body": {
    "settings": {
      "about_founder": "/media/uploads/1783596176453-0k2sjy.jpg",
      "about_team": "/media/uploads/1783596181374-co2zt8.png",
      "axis_images": "{\"social\":\"/media/uploads/1783595690737-ohqxfn.jpg\"}",
      "content_blocks": "{\"legal_privacy\":{\"fr\":\"## Confidentialité E2E e2e-1783804081013\",\"en\":\"## Confidentialité E2E e2e-1783804081013\"}}",
      "default_live_thumb": "/media/uploads/1783595957769-iabb0v.jpg",
      "default_news_cover": "/media/uploads/1783595833524-19tktd.jpg",
      "default_testimonial_1": "/media/uploads/1783596017675-nqq43o.jpg",
      "default_testimonial_2": "/media/uploads/1783596165273-w33lji.jpg",
      "default_testimonial_anonymous": "/media/uploads/1783596171417-xnd730.png",
      "donors_public": "0",
      "favicon_url": "/media/uploads/1783596192484-lyay9p.jpg",
      "fikin_gallery": "[]",
      "hero_image": "/media/uploads/1783595579061-m0ob7v.jpg",
      "hero_image_alt": "Hero E2E e2e-1783804081013",
      "hero_poster": "/media/hero/hero-home.png",
      "hero_video": "",
      "i18n_overrides": "{\"fr\":{\"nav.about\":\"À propos E2E e2e-1783804081013\"},\"en\":{\"nav.about\":\"About E2E e2e-1783804081013\"}}",
      "media_catalog": "[{\"path\":\"/media/uploads/1783596192484-lyay9p.jpg\",\"category\":\"defaults\",\"tags\":[\"defaults\"],\"uploaded_at\":\"2026-07-09T11:23:12.486Z\"},{\"path\":\"/media/uploads/1783596186176-wz9ryu.jpg\",\"category\":\"defaults\",\"tags\":[\"defaults\"],\"uploaded_at\":\"2026-07-09T11:23:06.182Z\"},{\"path\":\"/media/uploads/1783596181374-co2zt8.png\",\"category\":\"defaults\",\"tags\":[\"defaults\"],\"uploaded_at\":\"2026-07-09T11:23:01.376Z\"},{\"path\":\"/media/uploads/1783596176453-0k2sjy.jpg\",\"category\":\"defaults\",\"tags\":[\"defaults\"],\"uploaded_at\":\"2026-07-09T11:22:56.455Z\"},{\"path\":\"/media/uploads/1783596171417-xnd730.png\",\"category\":\"defaults\",\"tags\":[\"defaults\"],\"uploaded_at\":\"2026-07-09T11:22:51.419Z\"},{\"path\":\"/media/uploads/1783596165273-w33lji.jpg\",\"category\":\"defaults\",\"tags\":[\"defaults\"],\"uploaded_at\":\"2026-07-09T11:22:45.295Z\"},{\"path\":\"/media/uploads/1783596017675-nqq43o.jpg\",\"category\":\"defaults\",\"tags\":[\"defaults\"],\"uploaded_at\":\"2026-07-09T11:20:17.678Z\"},{\"path\":\"/media/uploads/1783595957769-iabb0v.jpg\",\"category\":\"defaults\",\"tags\":[\"defaults\"],\"uploaded_at\":\"2026-07-09T11:19:17.788Z\"},{\"path\":\"/media/uploads/1783595833524-19tktd.jpg\",\"category\":\"defaults\",\"tags\":[\"defaults\"],\"uploaded_at\":\"2026-07-09T11:17:13.532Z\"},{\"path\":\"/media/uploads/1783595732855-cwcu2j.jpg\",\"category\":\"defaults\",\"tags\":[\"defaults\"],\"uploaded_at\":\"2026-07-09T11:15:32.858Z\"},{\"path\":\"/media/uploads/1783595690737-ohqxfn.jpg\",\"category\":\"axes\",\"tags\":[\"axes\"],\"uploaded_at\":\"2026-07-09T11:14:50.740Z\"},{\"path\":\"/media/uploads/1783595640230-yv1bdd.jpg\",\"category\":\"hero\",\"tags\":[\"hero\"],\"uploaded_at\":\"2026-07-09T11:14:00.232Z\"},{\"path\":\"/media/uploads/1783595579061-m0ob7v.jpg\",\"category\":\"hero\",\"tags\":[\"hero\"],\"uploaded_at\":\"2026-07-09T11:12:59.082Z\"}]",
      "mission_image": "/media/uploads/1783595640230-yv1bdd.jpg",
      "og_image": "/media/uploads/1783596186176-wz9ryu.jpg",
      "petition_signatures_seen_at": "<volatile>",
      "site_country": "",
      "site_email": "contact-e2e-1783804081013@cfmasbl.com",
      "site_founded": "",
      "site_founder": "",
      "site_name": "",
      "site_phone": "0859588332",
      "site_quote": "",
      "site_sigle": "",
      "site_tagline": "Preview speed e2e-1783804081013",
      "social_links": "{\"facebook\":\"https://social-e2e-e2e-1783804081013.example.com\",\"twitter\":\"\",\"youtube\":\"\",\"linkedin\":\"\"}"
    }
  }
}